dependency/__init__.py
dependency/cli/__init__.py
dependency/cli/generation/__init__.py
dependency/cli/generation/base.py
dependency/cli/generation/component.py
dependency/cli/generation/instance.py
dependency/cli/generation/module.py
dependency/cli/generation/plugin.py
dependency/cli/models/__init__.py
dependency/cli/models/base.py
dependency/cli/templates/component.py.j2
dependency/cli/templates/instance.py.j2
dependency/cli/templates/module.py.j2
dependency/cli/templates/plugin.py.j2
dependency/core/__init__.py
dependency/core/exceptions.py
dependency/core/agrupation/__init__.py
dependency/core/agrupation/entrypoint.py
dependency/core/agrupation/module.py
dependency/core/agrupation/plugin.py
dependency/core/declaration/__init__.py
dependency/core/declaration/component.py
dependency/core/declaration/instance.py
dependency/core/declaration/product.py
dependency/core/injection/__init__.py
dependency/core/injection/base.py
dependency/core/injection/injectable.py
dependency/core/injection/provider.py
dependency/core/injection/wiring.py
dependency/core/resolution/__init__.py
dependency/core/resolution/container.py
dependency/core/resolution/errors.py
dependency/core/resolution/resolver.py
dependency/core/resolution/strategy.py
dependency/core/utils/cycle.py
dependency/core/utils/lazy.py
dependency-stubs/__init__.pyi
dependency-stubs/cli/__init__.pyi
dependency-stubs/cli/generation/__init__.pyi
dependency-stubs/cli/generation/base.pyi
dependency-stubs/cli/generation/component.pyi
dependency-stubs/cli/generation/instance.pyi
dependency-stubs/cli/generation/module.pyi
dependency-stubs/cli/generation/plugin.pyi
dependency-stubs/cli/models/__init__.pyi
dependency-stubs/cli/models/base.pyi
dependency-stubs/core/__init__.pyi
dependency-stubs/core/exceptions.pyi
dependency-stubs/core/agrupation/__init__.pyi
dependency-stubs/core/agrupation/base.pyi
dependency-stubs/core/agrupation/entrypoint.pyi
dependency-stubs/core/agrupation/module.pyi
module_dependency-0.5.0.dist-info/METADATA
module_dependency-0.5.0.dist-info/WHEEL
module_dependency-0.5.0.dist-info/licenses/LICENSE
module_dependency-0.5.0.dist-info/RECORD
