Metadata-Version: 2.4
Name: module_dependency
Version: 0.5.0
Summary: A dependency management tool for Python projects.
Project-URL: Homepage, https://github.com/fabaindaiz/module-injection
Project-URL: Documentation, https://github.com/fabaindaiz/module-dependency/tree/main/docs
Project-URL: Changelog, https://github.com/fabaindaiz/module-dependency/blob/main/CHANGELOG.md
Project-URL: Issues, https://github.com/fabaindaiz/module-injection/issues
Author-email: Fabian D <github.clapping767@passmail.net>
License-Expression: GPL-3.0-or-later
License-File: LICENSE
Keywords: dependency-injection,dependency-management
Classifier: Development Status :: 4 - Beta
Classifier: Intended Audience :: Developers
Classifier: Operating System :: OS Independent
Classifier: Programming Language :: Python :: 3
Classifier: Topic :: Software Development :: Libraries
Requires-Python: >=3.9
Requires-Dist: dependency-injector
Requires-Dist: jinja2
Requires-Dist: pydantic
Requires-Dist: pydantic-settings
